jade_config/__init__.py
jade_config/__main__.py
jade_config/config.py
jade_config-1.1.2.dist-info/METADATA
jade_config-1.1.2.dist-info/WHEEL
jade_config-1.1.2.dist-info/top_level.txt
jade_config-1.1.2.dist-info/RECORD
