Metadata-Version: 2.1
Name: jade-config
Version: 1.1.2
Summary: A python package to quickly and easily make configs, or other things that your program needs to remember.
Author-email: nfoert <jadesoftware1@gmail.com>
Project-URL: Homepage, https://github.com/nfoert/jade_config
Keywords: jade,jade_config,jade config,config,remember
Classifier: Programming Language :: Python
Classifier: Programming Language :: Python :: 3
Requires-Python: >=3.10
Provides-Extra: dev
